odoo10_addon_hs_code_link-10.0.1.0.0-py2.7-nspkg.pth
odoo/addons/hs_code_link/README.rst
odoo/addons/hs_code_link/__init__.py
odoo/addons/hs_code_link/__manifest__.py
odoo/addons/hs_code_link/models/__init__.py
odoo/addons/hs_code_link/models/product.py
odoo/addons/hs_code_link/views/product_views.xml
odoo10_addon_hs_code_link-10.0.1.0.0.dist-info/DESCRIPTION.rst
odoo10_addon_hs_code_link-10.0.1.0.0.dist-info/METADATA
odoo10_addon_hs_code_link-10.0.1.0.0.dist-info/RECORD
odoo10_addon_hs_code_link-10.0.1.0.0.dist-info/WHEEL
odoo10_addon_hs_code_link-10.0.1.0.0.dist-info/metadata.json
odoo10_addon_hs_code_link-10.0.1.0.0.dist-info/namespace_packages.txt
odoo10_addon_hs_code_link-10.0.1.0.0.dist-info/top_level.txt
